MANIFEST.in
README.txt
bootstrap.py
buildout.cfg
setup.py
docs/HISTORY.txt
docs/INSTALL.txt
docs/LICENSE.GPL
docs/LICENSE.txt
src/themetweaker/__init__.py
src/themetweaker.themeswitcher.egg-info/PKG-INFO
src/themetweaker.themeswitcher.egg-info/SOURCES.txt
src/themetweaker.themeswitcher.egg-info/dependency_links.txt
src/themetweaker.themeswitcher.egg-info/entry_points.txt
src/themetweaker.themeswitcher.egg-info/namespace_packages.txt
src/themetweaker.themeswitcher.egg-info/not-zip-safe
src/themetweaker.themeswitcher.egg-info/requires.txt
src/themetweaker.themeswitcher.egg-info/top_level.txt
src/themetweaker/themeswitcher/__init__.py
src/themetweaker/themeswitcher/configure.zcml
src/themetweaker/themeswitcher/form.py
src/themetweaker/themeswitcher/form.txt
src/themetweaker/themeswitcher/interfaces.py
src/themetweaker/themeswitcher/overrides.zcml
src/themetweaker/themeswitcher/profiles.zcml
src/themetweaker/themeswitcher/setuphandlers.py
src/themetweaker/themeswitcher/traverser.py
src/themetweaker/themeswitcher/utils.py
src/themetweaker/themeswitcher/Extensions/Install.py
src/themetweaker/themeswitcher/profiles/default/actions.xml
src/themetweaker/themeswitcher/profiles/default/metadata.xml
src/themetweaker/themeswitcher/profiles/default/themetweaker.themeswitcher_various.txt
src/themetweaker/themeswitcher/profiles/uninstall/actions.xml
src/themetweaker/themeswitcher/profiles/uninstall/themetweaker.themeswitcher_uninstall.txt
src/themetweaker/themeswitcher/tests/__init__.py
src/themetweaker/themeswitcher/tests/configure.zcml
src/themetweaker/themeswitcher/tests/test_base.py
src/themetweaker/themeswitcher/tests/test_installation.py
src/themetweaker/themeswitcher/tests/skin_one/__init__.py
src/themetweaker/themeswitcher/tests/skin_one/configure.zcml
src/themetweaker/themeswitcher/tests/skin_one/profiles.zcml
src/themetweaker/themeswitcher/tests/skin_one/browser/__init__.py
src/themetweaker/themeswitcher/tests/skin_one/browser/configure.zcml
src/themetweaker/themeswitcher/tests/skin_one/browser/interfaces.py
src/themetweaker/themeswitcher/tests/skin_one/browser/viewlet.pt
src/themetweaker/themeswitcher/tests/skin_one/browser/stylesheets/main.css
src/themetweaker/themeswitcher/tests/skin_one/profiles/default/cssregistry.xml
src/themetweaker/themeswitcher/tests/skin_one/profiles/default/metadata.xml
src/themetweaker/themeswitcher/tests/skin_one/profiles/default/skins.xml
