Metadata-Version: 1.0
Name: themetweaker.themeswitcher
Version: 1.0
Summary: A product for switching themes in Plone.
Home-page: https://weblion.psu.edu/trac/weblion/wiki/ThemeSwitcher
Author: Six Feet Up, Inc. <info at sixfeetup com> | WebLion Group, Penn State University
Author-email: support@weblion.psu.edu
License: GPL
Keywords: themeswitcher themetweaker theme switcher weblion
Platform: UNKNOWN
Classifier: Framework :: Plone
Classifier: Framework :: Zope2
Classifier: Programming Language :: Python
Classifier: Programming Language :: Python :: 2.4
Classifier: Topic :: Software Development :: Libraries :: Python Modules
Classifier: Intended Audience :: Developers
Classifier: Development Status :: 4 - Beta
